django_su/__init__.py
django_su/backends.py
django_su/compat.py
django_su/context_processors.py
django_su/forms.py
django_su/models.py
django_su/urls.py
django_su/utils.py
django_su/views.py
django_su/locale/pt_BR/LC_MESSAGES/django.mo
django_su/locale/pt_BR/LC_MESSAGES/django.po
django_su/locale/ru/LC_MESSAGES/django.mo
django_su/locale/ru/LC_MESSAGES/django.po
django_su/templates/admin/base_site.html
django_su/templates/admin/auth/user/change_form.html
django_su/templates/admin/auth/user/change_list.html
django_su/templates/su/is_su.html
django_su/templates/su/login.html
django_su/templates/su/login_link.html
django_su/templatetags/__init__.py
django_su/templatetags/compat.py
django_su/templatetags/su_tags.py
django_su-0.9.0.dist-info/LICENSE
django_su-0.9.0.dist-info/METADATA
django_su-0.9.0.dist-info/WHEEL
django_su-0.9.0.dist-info/top_level.txt
django_su-0.9.0.dist-info/RECORD
