Metadata-Version: 2.1
Name: django-su
Version: 0.9.0
Summary: Login as any user from the Django admin interface, then switch back when done
Home-page: http://github.com/adamcharnock/django-su
Author: Adam Charnock
Author-email: adam@adamcharnock.com
Maintainer: Basil Shubin
Maintainer-email: basil.shubin@gmail.com
License: MIT License
Download-URL: https://github.com/adamcharnock/django-su/zipball/master
Platform: UNKNOWN
Classifier: Development Status :: 5 - Production/Stable
Classifier: Environment :: Web Environment
Classifier: Framework :: Django
Classifier: Intended Audience :: Developers
Classifier: Intended Audience :: System Administrators
Classifier: License :: OSI Approved :: MIT License
Classifier: Operating System :: OS Independent
Classifier: Programming Language :: Python
Classifier: Programming Language :: Python :: 2
Classifier: Programming Language :: Python :: 2.7
Classifier: Programming Language :: Python :: 3
Classifier: Programming Language :: Python :: 3.4
Classifier: Programming Language :: Python :: 3.5
Classifier: Programming Language :: Python :: 3.6
Classifier: Programming Language :: Python :: 3.7
Classifier: Programming Language :: Python :: 3.8
Classifier: Topic :: Internet :: WWW/HTTP
Classifier: Topic :: Internet :: WWW/HTTP :: Dynamic Content
Requires: Django (>=1.11)
Requires-Dist: django (>=1.11)
